{
 "cells": [
  {
   "cell_type": "markdown",
   "id": "51e13d9b-35a1-4c0f-b8e1-9ff1e262287d",
   "metadata": {},
   "source": [
    "## test 1"
   ]
  },
  {
   "cell_type": "code",
   "execution_count": 1,
   "id": "65e0ea15-0ddd-4d12-9c28-28694283facf",
   "metadata": {},
   "outputs": [],
   "source": [
    "def f1(a):\n",
    "    print(a)\n",
    "    print(b)"
   ]
  },
  {
   "cell_type": "code",
   "execution_count": 2,
   "id": "fa89368d-3ba2-45bc-8748-dcf57e695c07",
   "metadata": {},
   "outputs": [
    {
     "name": "stdout",
     "output_type": "stream",
     "text": [
      "3\n"
     ]
    },
    {
     "ename": "NameError",
     "evalue": "name 'b' is not defined",
     "output_type": "error",
     "traceback": [
      "\u001b[0;31m---------------------------------------------------------------------------\u001b[0m",
      "\u001b[0;31mNameError\u001b[0m                                 Traceback (most recent call last)",
      "Cell \u001b[0;32mIn[2], line 1\u001b[0m\n\u001b[0;32m----> 1\u001b[0m \u001b[43mf1\u001b[49m\u001b[43m(\u001b[49m\u001b[38;5;241;43m3\u001b[39;49m\u001b[43m)\u001b[49m\n",
      "Cell \u001b[0;32mIn[1], line 3\u001b[0m, in \u001b[0;36mf1\u001b[0;34m(a)\u001b[0m\n\u001b[1;32m      1\u001b[0m \u001b[38;5;28;01mdef\u001b[39;00m \u001b[38;5;21mf1\u001b[39m(a):\n\u001b[1;32m      2\u001b[0m     \u001b[38;5;28mprint\u001b[39m(a)\n\u001b[0;32m----> 3\u001b[0m     \u001b[38;5;28mprint\u001b[39m(\u001b[43mb\u001b[49m)\n",
      "\u001b[0;31mNameError\u001b[0m: name 'b' is not defined"
     ]
    }
   ],
   "source": [
    "f1(3)"
   ]
  },
  {
   "cell_type": "markdown",
   "id": "bb78431b-8f60-4bf7-9723-b9ffacf2040d",
   "metadata": {},
   "source": [
    "## test 2"
   ]
  },
  {
   "cell_type": "code",
   "execution_count": 4,
   "id": "93619406-f182-4e65-b660-91de7978819a",
   "metadata": {},
   "outputs": [],
   "source": [
    "b = 6"
   ]
  },
  {
   "cell_type": "code",
   "execution_count": 5,
   "id": "e5e98c1e-b1e7-43b2-99b4-b3ea7a9fc87e",
   "metadata": {},
   "outputs": [
    {
     "name": "stdout",
     "output_type": "stream",
     "text": [
      "3\n",
      "6\n"
     ]
    }
   ],
   "source": [
    "f1(3)"
   ]
  },
  {
   "cell_type": "markdown",
   "id": "e6b0bafc-0127-48d6-b9e1-4172f87d8dfc",
   "metadata": {},
   "source": [
    "## test 3"
   ]
  },
  {
   "cell_type": "code",
   "execution_count": 6,
   "id": "5b8ce64d-65cc-49b5-a15a-64b819736d40",
   "metadata": {},
   "outputs": [],
   "source": [
    "b = 6\n",
    "def f2(a):\n",
    "    print(a)\n",
    "    print(b)\n",
    "    b = 9"
   ]
  },
  {
   "cell_type": "code",
   "execution_count": 7,
   "id": "eb3694b0-187e-40b7-a6c2-d2c9be976d77",
   "metadata": {},
   "outputs": [
    {
     "name": "stdout",
     "output_type": "stream",
     "text": [
      "3\n"
     ]
    },
    {
     "ename": "UnboundLocalError",
     "evalue": "local variable 'b' referenced before assignment",
     "output_type": "error",
     "traceback": [
      "\u001b[0;31m---------------------------------------------------------------------------\u001b[0m",
      "\u001b[0;31mUnboundLocalError\u001b[0m                         Traceback (most recent call last)",
      "Cell \u001b[0;32mIn[7], line 1\u001b[0m\n\u001b[0;32m----> 1\u001b[0m \u001b[43mf2\u001b[49m\u001b[43m(\u001b[49m\u001b[38;5;241;43m3\u001b[39;49m\u001b[43m)\u001b[49m\n",
      "Cell \u001b[0;32mIn[6], line 4\u001b[0m, in \u001b[0;36mf2\u001b[0;34m(a)\u001b[0m\n\u001b[1;32m      2\u001b[0m \u001b[38;5;28;01mdef\u001b[39;00m \u001b[38;5;21mf2\u001b[39m(a):\n\u001b[1;32m      3\u001b[0m     \u001b[38;5;28mprint\u001b[39m(a)\n\u001b[0;32m----> 4\u001b[0m     \u001b[38;5;28mprint\u001b[39m(\u001b[43mb\u001b[49m)\n\u001b[1;32m      5\u001b[0m     b \u001b[38;5;241m=\u001b[39m \u001b[38;5;241m9\u001b[39m\n",
      "\u001b[0;31mUnboundLocalError\u001b[0m: local variable 'b' referenced before assignment"
     ]
    }
   ],
   "source": [
    "f2(3)"
   ]
  },
  {
   "cell_type": "markdown",
   "id": "79d18767-c37b-4aad-a11c-3f51bb7dad9c",
   "metadata": {},
   "source": [
    "## test 4"
   ]
  },
  {
   "cell_type": "code",
   "execution_count": 8,
   "id": "30d909fe-b74f-478f-8867-80cac00c6ad4",
   "metadata": {},
   "outputs": [],
   "source": [
    "b = 6\n",
    "def f3(a):\n",
    "    global b\n",
    "    print(a)\n",
    "    print(b)\n",
    "    b = 9"
   ]
  },
  {
   "cell_type": "code",
   "execution_count": 9,
   "id": "ef9e0225-d88d-4ec3-9138-61fa3856e69c",
   "metadata": {},
   "outputs": [
    {
     "name": "stdout",
     "output_type": "stream",
     "text": [
      "3\n",
      "6\n"
     ]
    }
   ],
   "source": [
    "f3(3)"
   ]
  },
  {
   "cell_type": "code",
   "execution_count": 10,
   "id": "91605705-b66a-428c-ae60-4fb69e59278d",
   "metadata": {},
   "outputs": [
    {
     "data": {
      "text/plain": [
       "9"
      ]
     },
     "execution_count": 10,
     "metadata": {},
     "output_type": "execute_result"
    }
   ],
   "source": [
    "b"
   ]
  },
  {
   "cell_type": "markdown",
   "id": "d76d3a31-8fb7-4908-8ac7-d6aee5012ab6",
   "metadata": {},
   "source": [
    "## dis.dis"
   ]
  },
  {
   "cell_type": "code",
   "execution_count": 11,
   "id": "3a1c1e48-7e1c-455a-bdd7-3ab20c451e76",
   "metadata": {},
   "outputs": [],
   "source": [
    "from dis import dis"
   ]
  },
  {
   "cell_type": "code",
   "execution_count": 12,
   "id": "99461b44-bfe0-4b38-816e-8832e35e4f4d",
   "metadata": {},
   "outputs": [
    {
     "name": "stdout",
     "output_type": "stream",
     "text": [
      "  2           0 LOAD_GLOBAL              0 (print)\n",
      "              2 LOAD_FAST                0 (a)\n",
      "              4 CALL_FUNCTION            1\n",
      "              6 POP_TOP\n",
      "\n",
      "  3           8 LOAD_GLOBAL              0 (print)\n",
      "             10 LOAD_GLOBAL              1 (b)\n",
      "             12 CALL_FUNCTION            1\n",
      "             14 POP_TOP\n",
      "             16 LOAD_CONST               0 (None)\n",
      "             18 RETURN_VALUE\n"
     ]
    }
   ],
   "source": [
    "dis(f1)"
   ]
  },
  {
   "cell_type": "code",
   "execution_count": 13,
   "id": "534b6bb8-046f-4d92-84f7-a2258fa651f1",
   "metadata": {},
   "outputs": [
    {
     "name": "stdout",
     "output_type": "stream",
     "text": [
      "  3           0 LOAD_GLOBAL              0 (print)\n",
      "              2 LOAD_FAST                0 (a)\n",
      "              4 CALL_FUNCTION            1\n",
      "              6 POP_TOP\n",
      "\n",
      "  4           8 LOAD_GLOBAL              0 (print)\n",
      "             10 LOAD_FAST                1 (b)\n",
      "             12 CALL_FUNCTION            1\n",
      "             14 POP_TOP\n",
      "\n",
      "  5          16 LOAD_CONST               1 (9)\n",
      "             18 STORE_FAST               1 (b)\n",
      "             20 LOAD_CONST               0 (None)\n",
      "             22 RETURN_VALUE\n"
     ]
    }
   ],
   "source": [
    "dis(f2)"
   ]
  },
  {
   "cell_type": "code",
   "execution_count": null,
   "id": "0e38d5b3-e407-411b-85d0-0ae3edf4e68b",
   "metadata": {},
   "outputs": [],
   "source": []
  }
 ],
 "metadata": {
  "kernelspec": {
   "display_name": "Python 3 (ipykernel)",
   "language": "python",
   "name": "python3"
  },
  "language_info": {
   "codemirror_mode": {
    "name": "ipython",
    "version": 3
   },
   "file_extension": ".py",
   "mimetype": "text/x-python",
   "name": "python",
   "nbconvert_exporter": "python",
   "pygments_lexer": "ipython3",
   "version": "3.10.6"
  }
 },
 "nbformat": 4,
 "nbformat_minor": 5
}
